ament_cmake_test/_dummy.cpython-310-x86_64-linux-gnu.so
ros_ament_cmake_test-2.7.3.data/data/lib/python3.10/site-packages/ament_cmake_test/__init__.py
ros_ament_cmake_test-2.7.3.data/data/lib/python3.10/site-packages/ament_cmake_test/__pycache__/__init__.cpython-310.pyc
ros_ament_cmake_test-2.7.3.data/data/lib/python3.10/site-packages/ament_cmake_test-2.7.3-py3.10.egg-info/PKG-INFO
ros_ament_cmake_test-2.7.3.data/data/lib/python3.10/site-packages/ament_cmake_test-2.7.3-py3.10.egg-info/SOURCES.txt
ros_ament_cmake_test-2.7.3.data/data/lib/python3.10/site-packages/ament_cmake_test-2.7.3-py3.10.egg-info/dependency_links.txt
ros_ament_cmake_test-2.7.3.data/data/lib/python3.10/site-packages/ament_cmake_test-2.7.3-py3.10.egg-info/top_level.txt
ros_ament_cmake_test-2.7.3.data/data/share/ament_cmake_test/local_setup.bash
ros_ament_cmake_test-2.7.3.data/data/share/ament_cmake_test/local_setup.dsv
ros_ament_cmake_test-2.7.3.data/data/share/ament_cmake_test/local_setup.sh
ros_ament_cmake_test-2.7.3.data/data/share/ament_cmake_test/local_setup.zsh
ros_ament_cmake_test-2.7.3.data/data/share/ament_cmake_test/package.dsv
ros_ament_cmake_test-2.7.3.data/data/share/ament_cmake_test/package.xml
ros_ament_cmake_test-2.7.3.data/data/share/ament_cmake_test/cmake/ament_add_test.cmake
ros_ament_cmake_test-2.7.3.data/data/share/ament_cmake_test/cmake/ament_add_test_label.cmake
ros_ament_cmake_test-2.7.3.data/data/share/ament_cmake_test/cmake/ament_cmake_test-extras.cmake
ros_ament_cmake_test-2.7.3.data/data/share/ament_cmake_test/cmake/ament_cmake_testConfig-version.cmake
ros_ament_cmake_test-2.7.3.data/data/share/ament_cmake_test/cmake/ament_cmake_testConfig.cmake
ros_ament_cmake_test-2.7.3.data/data/share/ament_cmake_test/cmake/run_test.py
ros_ament_cmake_test-2.7.3.data/data/share/ament_cmake_test/environment/ament_prefix_path.dsv
ros_ament_cmake_test-2.7.3.data/data/share/ament_cmake_test/environment/ament_prefix_path.sh
ros_ament_cmake_test-2.7.3.data/data/share/ament_cmake_test/environment/path.dsv
ros_ament_cmake_test-2.7.3.data/data/share/ament_cmake_test/environment/path.sh
ros_ament_cmake_test-2.7.3.data/data/share/ament_cmake_test/environment/pythonpath.dsv
ros_ament_cmake_test-2.7.3.data/data/share/ament_cmake_test/environment/pythonpath.sh
ros_ament_cmake_test-2.7.3.data/data/share/ament_index/resource_index/package_run_dependencies/ament_cmake_test
ros_ament_cmake_test-2.7.3.dist-info/METADATA
ros_ament_cmake_test-2.7.3.dist-info/WHEEL
ros_ament_cmake_test-2.7.3.dist-info/top_level.txt
ros_ament_cmake_test-2.7.3.dist-info/RECORD
