Metadata-Version: 2.4
Name: ros-ament-cmake-test
Version: 2.7.3
Summary: Wheel for the ament_cmake_test (ros-ament-cmake-test) ROS 2 package.
Dynamic: description
Dynamic: description-content-type
Dynamic: summary
